odoo/addons/website_account_fiscal_position_partner_type/README.rst
odoo/addons/website_account_fiscal_position_partner_type/__init__.py
odoo/addons/website_account_fiscal_position_partner_type/__manifest__.py
odoo/addons/website_account_fiscal_position_partner_type/controllers/__init__.py
odoo/addons/website_account_fiscal_position_partner_type/controllers/main.py
odoo/addons/website_account_fiscal_position_partner_type/i18n/es.po
odoo/addons/website_account_fiscal_position_partner_type/i18n/website_account_fiscal_position_partner_type.pot
odoo/addons/website_account_fiscal_position_partner_type/readme/CONTRIBUTORS.rst
odoo/addons/website_account_fiscal_position_partner_type/readme/DESCRIPTION.rst
odoo/addons/website_account_fiscal_position_partner_type/readme/USAGE.rst
odoo/addons/website_account_fiscal_position_partner_type/static/description/icon.png
odoo/addons/website_account_fiscal_position_partner_type/static/description/index.html
odoo/addons/website_account_fiscal_position_partner_type/views/website_sale.xml
odoo13_addon_website_account_fiscal_position_partner_type-13.0.0.0.2.dev6.dist-info/METADATA
odoo13_addon_website_account_fiscal_position_partner_type-13.0.0.0.2.dev6.dist-info/WHEEL
odoo13_addon_website_account_fiscal_position_partner_type-13.0.0.0.2.dev6.dist-info/top_level.txt
odoo13_addon_website_account_fiscal_position_partner_type-13.0.0.0.2.dev6.dist-info/RECORD
