Metadata-Version: 2.1
Name: odoo13-addon-website-account-fiscal-position-partner-type
Version: 13.0.0.0.2.dev6
Summary: Website Account Fiscal Position Partner Type
Home-page: https://github.com/OCA/e-commerce
Author: Sygel Technology,Odoo Community Association (OCA)
Author-email: support@odoo-community.org
License: AGPL-3
Platform: UNKNOWN
Classifier: Programming Language :: Python
Classifier: Framework :: Odoo
Classifier: Framework :: Odoo :: 13.0
Classifier: License :: OSI Approved :: GNU Affero General Public License v3
Classifier: Development Status :: 4 - Beta
Requires-Python: >=3.5
Requires-Dist: odoo13-addon-account-fiscal-position-partner-type
Requires-Dist: odoo <13.1dev,>=13.0a
